setup.py
Pythine/__init__.py
Pythine/pythine.py
Pythine.egg-info/PKG-INFO
Pythine.egg-info/SOURCES.txt
Pythine.egg-info/dependency_links.txt
Pythine.egg-info/top_level.txt