Metadata-Version: 1.0
Name: Pythine
Version: 0.0.1
Summary: Pythine is an extremely lightweight python multi-threaded framework for agile multi-thread programming. With a single decorator before the function, your function will automatically be executed in multiple threads. 
Home-page: https://github.com/XericZephyr/Pythine
Author: Zheng Xu
Author-email: xuzheng1111@gmail.com
License: MIT
Keywords: python,multi-thread programming
Platform: UNKNOWN
